megamap/__init__.py
megamap/megamap.py
megamap-1.0.1.dist-info/METADATA
megamap-1.0.1.dist-info/WHEEL
megamap-1.0.1.dist-info/entry_points.txt
megamap-1.0.1.dist-info/RECORD
