Metadata-Version: 2.4
Name: megamap
Version: 1.0.1
Summary: Generate a visual map of your codebase
Author-email: Hrothgar <hrothgarrrr@gmail.com>
Requires-Python: >=3.7
Requires-Dist: drawsvg
Requires-Dist: pygments
